CandidateEliminationAlgorithm.py
ConceptLearning.py
FindSAlgorithm.py
conceptlearning/CandidateEliminationAlgorithm.py
conceptlearning/ConceptLearning.py
conceptlearning/FindSAlgorithm.py
conceptlearning/__init__.py
conceptlearning-0.0.8.dist-info/LICENSE.txt
conceptlearning-0.0.8.dist-info/METADATA
conceptlearning-0.0.8.dist-info/WHEEL
conceptlearning-0.0.8.dist-info/top_level.txt
conceptlearning-0.0.8.dist-info/RECORD
